requests_oidc/__init__.py
requests_oidc/__main__.py
requests_oidc/cli.py
requests_oidc/exceptions.py
requests_oidc/flows/__init__.py
requests_oidc/flows/auth_code.py
requests_oidc/flows/client_credentials.py
requests_oidc/flows/device_code.py
requests_oidc/flows/token.py
requests_oidc/flows/utils.py
requests_oidc/plugins.py
requests_oidc/types.py
requests_oidc/utils/__init__.py
requests_oidc/utils/catcher.py
requests_oidc/utils/discovery.py
requests_oidc/utils/scope.py
requests_oidc-0.6.1.dist-info/LICENSE
requests_oidc-0.6.1.dist-info/METADATA
requests_oidc-0.6.1.dist-info/WHEEL
requests_oidc-0.6.1.dist-info/entry_points.txt
requests_oidc-0.6.1.dist-info/RECORD
