Metadata-Version: 2.1
Name: requests-oidc
Version: 0.6.1
Summary: 
Home-page: https://github.com/tsweeney-dust/requests-oidc
License: MIT
Author: Tristan Sweeney
Author-email: tsweeney@dustidentity.com
Requires-Python: >=3.7,<4
Classifier: Development Status :: 3 - Alpha
Classifier: License :: OSI Approved :: MIT License
Classifier: Programming Language :: Python :: 3
Classifier: Programming Language :: Python :: 3.7
Classifier: Programming Language :: Python :: 3.8
Classifier: Programming Language :: Python :: 3.9
Classifier: Programming Language :: Python :: 3.10
Classifier: Programming Language :: Python :: 3.11
Requires-Dist: appdirs (>=1.4.4,<2.0.0)
Requires-Dist: qrcode (>=7.4.2,<8.0.0)
Requires-Dist: requests (>=2.28.1,<3.0.0)
Requires-Dist: requests-oauthlib (>=1.3.1,<2.0.0)
Requires-Dist: typer (>=0.9.0,<0.10.0)
Project-URL: Documentation, https://requests-oidc.readthedocs.io/en/latest/
Project-URL: Repository, https://github.com/tsweeney-dust/requests-oidc
